physical_propagation/__init__.py
physical_propagation/acoustic_losses.py
physical_propagation/propagate.py
physical_propagation/ray_tracing/__init__.py
physical_propagation/ray_tracing/ray_tracing.py
physical_propagation/ray_tracing/sound_speed_profile.py
physical_propagation-0.6.1.dist-info/LICENSE.txt
physical_propagation-0.6.1.dist-info/METADATA
physical_propagation-0.6.1.dist-info/WHEEL
physical_propagation-0.6.1.dist-info/top_level.txt
physical_propagation-0.6.1.dist-info/RECORD
