Metadata-Version: 2.1
Name: physical-propagation
Version: 0.6.1
Summary: A collection of code to determine how the acoustic levels propagating through the air will be altered
Home-page: https://gitlab.com/physicalpropagation/physcial_propagation
Author: Frank Mobley, Gregory Bowers, Alan T. Wall, S. Conner Campbell
Author-email: frank.mobley.1@afrl.af.mil
License: MIT
License-File: LICENSE.txt
Requires-Dist: numpy
Requires-Dist: scipy
Requires-Dist: PythonCoordinates (>=0.5.1)
Requires-Dist: PyTimbre (>=0.6.1)
